au/SettingsBase.py
au/__init__.py
au/__main__.py
au/classroom/AssignmentSettings.py
au/classroom/Roster.py
au/classroom/__init__.py
au/classroom/classroom_api.py
au/classroom/classroom_types.py
au/classroom/gh.py
au/cli/__init__.py
au/cli/cli.py
au/cli/assignment/__init__.py
au/cli/assignment/cli.py
au/cli/assignment/clone_all.py
au/cli/assignment/commit_all.py
au/cli/assignment/rename_roster.py
au/cli/assignment/time_details.py
au/cli/python/__init__.py
au/cli/python/cli.py
au/cli/python/eval_assignment.py
au/cli/python/gen_feedback.py
au/cli/python/gen_grades_csv.py
au/cli/python/pytest_data.py
au/cli/python/pytest_reporter.py
au/cli/python/quick_grade.py
au/cli/python/scoring.py
au/cli/repo/__init__.py
au/cli/repo/cli.py
au/cli/repo/create.py
au/cli/sql/__init__.py
au/cli/sql/cli.py
au/cli/sql/query_file.py
au/cli/sql/HOLD/all-feedback.sh
au/cli/sql/HOLD/all-scores.sh
au/cli/sql/HOLD/commonsql.py
au/cli/sql/HOLD/commonutil.py
au/cli/sql/HOLD/feedback.py
au/cli/sql/HOLD/feedback_score.py
au/cli/sql/HOLD/gen-score-csv.py
au/cli/sql/HOLD/gen-template.sh
au/cli/sql/HOLD/gensanity.py
au/cli/sql/HOLD/grades.csv
au/cli/sql/HOLD/props.py
au/cli/sql/HOLD/sanity.py
au/cli/sql/HOLD/similarity.py
au/click/AliasedGroup.py
au/click/AssignmentOptions.py
au/click/BasePathType.py
au/click/DebugOptions.py
au/click/RosterOptions.py
au/click/SubdirGroup.py
au/click/__init__.py
au/common/__init__.py
au/common/csv.py
au/common/datetime.py
au/common/drawing.py
au/common/terminal.py
au/common/_archive/label_dir.py
f_table/__init__.py
f_table/f_table.py
f_table/table_styles.py
f_table/terminal.py
git_wrap/__init__.py
git_wrap/git_repo.py
au_tools-0.1.6.dist-info/METADATA
au_tools-0.1.6.dist-info/WHEEL
au_tools-0.1.6.dist-info/entry_points.txt
au_tools-0.1.6.dist-info/licenses/LICENSE
au_tools-0.1.6.dist-info/RECORD
