Metadata-Version: 2.4
Name: au-tools
Version: 0.1.6
Summary: au - GitHub Classroom Automation Tools
Project-URL: homepage, https://ptyork.github.io/au
Project-URL: repository, https://github.com/ptyork/au
Project-URL: Bug Tracker, https://github.com/ptyork/au/issues
Author-email: Paul York <paul@yorkfamily.com>
License-Expression: MIT
License-File: LICENSE
Keywords: autograde,automation,classroom,codespaces,github
Requires-Python: <4.0,>=3.12
Requires-Dist: beaupy<4.0.0,>=3.10.1
Requires-Dist: click<9.0.0,>=8.1.8
Requires-Dist: dacite<2.0.0,>=1.9.2
Requires-Dist: pylint<4.0.0,>=3.3.4
Requires-Dist: pytest-subtests<0.15.0,>=0.14.1
Requires-Dist: pytest-timeout<3.0.0,>=2.3.1
Requires-Dist: pytest<9.0.0,>=8.3.4
Requires-Dist: rich<14.0.0,>=13.9.4
Requires-Dist: tomlkit<0.14.0,>=0.13.2
